{
  "openapi": "3.0.1",
  "info": {
    "title": "INDWalks",
    "version": "1.0"
  },
  "paths": {
    "/api/Regions": {
      "get": {
        "tags": [
          "Regions"
        ],
        "responses": {
          "200": {
            "description": "OK"
          }
        }
      },
      "post": {
        "tags": [
          "Regions"
        ],
        "requestBody": {
          "content": {
            "application/json": {
              "schema": {
                "$ref": "#/components/schemas/AddRegionRequestDto"
              }
            },
            "text/json": {
              "schema": {
                "$ref": "#/components/schemas/AddRegionRequestDto"
              }
            },
            "application/*+json": {
              "schema": {
                "$ref": "#/components/schemas/AddRegionRequestDto"
              }
            }
          }
        },
        "responses": {
          "200": {
            "description": "OK"
          }
        }
      }
    },
    "/api/Regions/{id}": {
      "get": {
        "tags": [
          "Regions"
        ],
        "parameters": [
          {
            "name": "id",
            "in": "path",
            "required": true,
            "schema": {
              "type": "string",
              "format": "uuid"
            }
          }
        ],
        "responses": {
          "200": {
            "description": "OK"
          }
        }
      },
      "put": {
        "tags": [
          "Regions"
        ],
        "parameters": [
          {
            "name": "id",
            "in": "path",
            "required": true,
            "schema": {
              "type": "string",
              "format": "uuid"
            }
          }
        ],
        "requestBody": {
          "content": {
            "application/json": {
              "schema": {
                "$ref": "#/components/schemas/UpdateRegionRequestDto"
              }
            },
            "text/json": {
              "schema": {
                "$ref": "#/components/schemas/UpdateRegionRequestDto"
              }
            },
            "application/*+json": {
              "schema": {
                "$ref": "#/components/schemas/UpdateRegionRequestDto"
              }
            }
          }
        },
        "responses": {
          "200": {
            "description": "OK"
          }
        }
      },
      "delete": {
        "tags": [
          "Regions"
        ],
        "parameters": [
          {
            "name": "id",
            "in": "path",
            "required": true,
            "schema": {
              "type": "string",
              "format": "uuid"
            }
          }
        ],
        "responses": {
          "200": {
            "description": "OK"
          }
        }
      }
    },
    "/api/Walks": {
      "post": {
        "tags": [
          "Walks"
        ],
        "requestBody": {
          "content": {
            "application/json": {
              "schema": {
                "$ref": "#/components/schemas/WalksRequestDTO"
              }
            },
            "text/json": {
              "schema": {
                "$ref": "#/components/schemas/WalksRequestDTO"
              }
            },
            "application/*+json": {
              "schema": {
                "$ref": "#/components/schemas/WalksRequestDTO"
              }
            }
          }
        },
        "responses": {
          "200": {
            "description": "OK"
          }
        }
      },
      "get": {
        "tags": [
          "Walks"
        ],
        "parameters": [
          {
            "name": "filterOn",
            "in": "query",
            "schema": {
              "type": "string"
            }
          },
          {
            "name": "filterquery",
            "in": "query",
            "schema": {
              "type": "string"
            }
          },
          {
            "name": "sortby",
            "in": "query",
            "schema": {
              "type": "string"
            }
          },
          {
            "name": "isAscending",
            "in": "query",
            "schema": {
              "type": "boolean"
            }
          },
          {
            "name": "pagenumber",
            "in": "query",
            "schema": {
              "type": "integer",
              "format": "int32"
            }
          },
          {
            "name": "pagesize",
            "in": "query",
            "schema": {
              "type": "integer",
              "format": "int32"
            }
          }
        ],
        "responses": {
          "200": {
            "description": "OK"
          }
        }
      }
    },
    "/api/Walks/{id}": {
      "get": {
        "tags": [
          "Walks"
        ],
        "parameters": [
          {
            "name": "id",
            "in": "path",
            "required": true,
            "schema": {
              "type": "string",
              "format": "uuid"
            }
          }
        ],
        "responses": {
          "200": {
            "description": "OK"
          }
        }
      },
      "put": {
        "tags": [
          "Walks"
        ],
        "parameters": [
          {
            "name": "id",
            "in": "path",
            "required": true,
            "schema": {
              "type": "string",
              "format": "uuid"
            }
          }
        ],
        "requestBody": {
          "content": {
            "application/json": {
              "schema": {
                "$ref": "#/components/schemas/UpdateWalkRequestDTO"
              }
            },
            "text/json": {
              "schema": {
                "$ref": "#/components/schemas/UpdateWalkRequestDTO"
              }
            },
            "application/*+json": {
              "schema": {
                "$ref": "#/components/schemas/UpdateWalkRequestDTO"
              }
            }
          }
        },
        "responses": {
          "200": {
            "description": "OK"
          }
        }
      },
      "delete": {
        "tags": [
          "Walks"
        ],
        "parameters": [
          {
            "name": "id",
            "in": "path",
            "required": true,
            "schema": {
              "type": "string",
              "format": "uuid"
            }
          }
        ],
        "responses": {
          "200": {
            "description": "OK"
          }
        }
      }
    }
  },
  "components": {
    "schemas": {
      "AddRegionRequestDto": {
        "required": [
          "code",
          "name"
        ],
        "type": "object",
        "properties": {
          "code": {
            "maxLength": 10,
            "minLength": 2,
            "type": "string"
          },
          "name": {
            "maxLength": 50,
            "minLength": 5,
            "type": "string"
          },
          "regionImageUrl": {
            "type": "string",
            "nullable": true
          }
        },
        "additionalProperties": false
      },
      "UpdateRegionRequestDto": {
        "required": [
          "code",
          "name"
        ],
        "type": "object",
        "properties": {
          "code": {
            "maxLength": 10,
            "minLength": 2,
            "type": "string"
          },
          "name": {
            "maxLength": 50,
            "minLength": 5,
            "type": "string"
          },
          "regionImageUrl": {
            "type": "string",
            "nullable": true
          }
        },
        "additionalProperties": false
      },
      "UpdateWalkRequestDTO": {
        "required": [
          "description",
          "difficultyId",
          "lengthInKm",
          "name",
          "regionId"
        ],
        "type": "object",
        "properties": {
          "name": {
            "maxLength": 50,
            "minLength": 5,
            "type": "string"
          },
          "description": {
            "maxLength": 5000,
            "minLength": 30,
            "type": "string"
          },
          "lengthInKm": {
            "maximum": 100,
            "minimum": 0.1,
            "type": "number",
            "format": "double"
          },
          "walkImageUrl": {
            "type": "string",
            "nullable": true
          },
          "difficultyId": {
            "type": "string",
            "format": "uuid"
          },
          "regionId": {
            "type": "string",
            "format": "uuid"
          }
        },
        "additionalProperties": false
      },
      "WalksRequestDTO": {
        "required": [
          "description",
          "difficultyId",
          "lengthInKm",
          "name",
          "regionId"
        ],
        "type": "object",
        "properties": {
          "name": {
            "maxLength": 50,
            "minLength": 5,
            "type": "string"
          },
          "description": {
            "maxLength": 5000,
            "minLength": 30,
            "type": "string"
          },
          "lengthInKm": {
            "maximum": 100,
            "minimum": 0.1,
            "type": "number",
            "format": "double"
          },
          "walkImageUrl": {
            "type": "string",
            "nullable": true
          },
          "difficultyId": {
            "type": "string",
            "format": "uuid"
          },
          "regionId": {
            "type": "string",
            "format": "uuid"
          }
        },
        "additionalProperties": false
      }
    }
  }
}